Abg/__init__.py
Abg/config.py
Abg/helpers/__init__.py
Abg/helpers/get_user.py
Abg/helpers/helpers.py
Abg/helpers/http_helper.py
Abg/helpers/human_read.py
Abg/helpers/msg_types.py
Abg/helpers/parser.py
Abg/helpers/pyro_progress.py
Abg/helpers/ratelimit.py
Abg/helpers/string.py
Abg/inline/__init__.py
Abg/inline/inline_keyboard.py
Abg/inline/inline_pagination_keyboard.py
Abg/inline/reply_keyboard.py
Abg/patch/__init__.py
Abg/patch/bound/__init__.py
Abg/patch/bound/message.py
Abg/patch/decorators/__init__.py
Abg/patch/decorators/adminsOnly.py
Abg/patch/decorators/on_cb.py
Abg/patch/decorators/on_cmd.py
Abg/patch/decorators/utils.py
Abg/patch/methods/__init__.py
Abg/patch/methods/edit_message_text.py
Abg/patch/methods/send_as_file.py
Abg/patch/methods/send_message.py
Abg-2.3.6.dev0.dist-info/LICENSE
Abg-2.3.6.dev0.dist-info/METADATA
Abg-2.3.6.dev0.dist-info/WHEEL
Abg-2.3.6.dev0.dist-info/top_level.txt
Abg-2.3.6.dev0.dist-info/RECORD
