Metadata-Version: 2.1
Name: Abg
Version: 2.3.6.dev0
Summary: add-on for Pyrogram || Telegram bot helpers || Easy botting
Home-page: https://github.com/Abishnoi69/Abg
Download-URL: https://github.com/Abishnoi69/Abg/releases/latest
Author: Abishnoi
Author-email: Abishnoi69@Abg.org
License: MIT
Project-URL: Tracker, https://github.com/Abishnoi69/Abg/issues
Project-URL: Community, https://t.me/Abgpy
Project-URL: Source, https://github.com/Abishnoi69/Abg
Project-URL: Documentation, https://github.com/Abishnoi69/Abg/tree/master/doce
Keywords: add-on pyrogram bots telegram bot chat messenger mtproto api client library python conversation keyboard userbot patch https
Classifier: Development Status :: 5 - Production/Stable
Classifier: Intended Audience :: Developers
Classifier: Natural Language :: English
Classifier: Operating System :: OS Independent
Classifier: Programming Language :: Python
Classifier: Programming Language :: Python :: 3
Classifier: Programming Language :: Python :: 3.7
Classifier: Programming Language :: Python :: 3.8
Classifier: Programming Language :: Python :: 3.9
Classifier: Programming Language :: Python :: 3.10
Classifier: Programming Language :: Python :: 3.11
Classifier: Programming Language :: Python :: Implementation
Classifier: Programming Language :: Python :: Implementation :: CPython
Classifier: Programming Language :: Python :: Implementation :: PyPy
Classifier: Topic :: Internet
Classifier: Topic :: Communications
Classifier: Topic :: Communications :: Chat
Classifier: Topic :: Software Development :: Libraries
Classifier: Topic :: Software Development :: Libraries :: Python Modules
Classifier: Topic :: Software Development :: Libraries :: Application Frameworks
Requires-Python: ~=3.7
License-File: LICENSE
Requires-Dist: pytz >=2023.3
